bob/__init__.py
bob/api.py
bob/bob.py
bob/cli.py
bob/common.py
bob/compat.py
bob/debug.py
bob/modules.py
bob/typehints.py
bob/tasks/__init__.py
bob/tasks/bootstrap.py
bob/tasks/build.py
bob/tasks/configure.py
bob/tasks/format.py
bob/tasks/install.py
bob/tasks/test.py
bob/templates/FindBob.cmake
bob_the_developer-0.2.5.dist-info/LICENSE
bob_the_developer-0.2.5.dist-info/METADATA
bob_the_developer-0.2.5.dist-info/WHEEL
bob_the_developer-0.2.5.dist-info/entry_points.txt
bob_the_developer-0.2.5.dist-info/top_level.txt
bob_the_developer-0.2.5.dist-info/RECORD
