Metadata-Version: 2.1
Name: bob-the-developer
Version: 0.2.5
Summary: A collection of scripts to build C++ projects
Author: René Moll
License: MIT License
Project-URL: Repository, https://github.com/renemoll/bob
Project-URL: Issues, https://github.com/renemoll/bob/issues
Keywords: build tool,c++
Classifier: Development Status :: 3 - Alpha
Classifier: Environment :: Console
Classifier: Intended Audience :: Developers
Classifier: License :: OSI Approved :: MIT License
Classifier: Programming Language :: Python :: 3
Classifier: Programming Language :: Python :: 3.8
Classifier: Programming Language :: Python :: 3.9
Classifier: Programming Language :: Python :: 3.10
Classifier: Programming Language :: Python :: 3.11
Classifier: Programming Language :: Python :: 3.12
Classifier: Topic :: Software Development
Classifier: Topic :: Software Development :: Build Tools
Requires-Python: >=3.8
License-File: LICENSE
Requires-Dist: docopt
Requires-Dist: toml
Provides-Extra: dev
Requires-Dist: black ; extra == 'dev'
Requires-Dist: pre-commit ; extra == 'dev'
Requires-Dist: pydoclint ; extra == 'dev'
Requires-Dist: pylint ; extra == 'dev'
Requires-Dist: pytest ; extra == 'dev'
Requires-Dist: pytest-cov ; extra == 'dev'
Requires-Dist: pytest-mock ; extra == 'dev'
Requires-Dist: ruff ; extra == 'dev'
Requires-Dist: mypy ; extra == 'dev'
Requires-Dist: types-docopt ; extra == 'dev'
Requires-Dist: types-toml ; extra == 'dev'
Provides-Extra: test
Requires-Dist: docopt ; extra == 'test'
Requires-Dist: pytest >=7.4 ; extra == 'test'
Requires-Dist: pytest-cov ; extra == 'test'
Requires-Dist: pytest-mock ; extra == 'test'
Requires-Dist: toml ; extra == 'test'
Provides-Extra: tox
Requires-Dist: tox >=4.0 ; extra == 'tox'
